bbm_mates/__init__.py
bbm_mates/controller.py
bbm_mates_controller-1.0.2.dist-info/LICENSE
bbm_mates_controller-1.0.2.dist-info/METADATA
bbm_mates_controller-1.0.2.dist-info/WHEEL
bbm_mates_controller-1.0.2.dist-info/top_level.txt
bbm_mates_controller-1.0.2.dist-info/RECORD
