Metadata-Version: 2.1
Name: bbm-mates-controller
Version: 1.0.2
Summary: A Python Library developed to be used with Mates Studio Commander or Architect Environment and BBM modules connected using BBM programmer or similar USB-to UART modules
Home-page: https://github.com/BreadBoardMates/BBM-Python-Mates-Controller
Author: Breadboard Mates
Author-email: developers@breadboardmates.com
License: UNKNOWN
Project-URL: Bug Tracker, https://github.com/BreadBoardMates/BBM-Python-Mates-Controller/issues
Platform: UNKNOWN
Classifier: Programming Language :: Python :: 3
Classifier: License :: OSI Approved :: MIT License
Classifier: Operating System :: OS Independent
Requires-Python: >=3.6
License-File: LICENSE
Requires-Dist: mates-controller
